PuneetPackage.py
puneetpackage-0.0.3.dist-info/LICENSE
puneetpackage-0.0.3.dist-info/METADATA
puneetpackage-0.0.3.dist-info/WHEEL
puneetpackage-0.0.3.dist-info/top_level.txt
puneetpackage-0.0.3.dist-info/RECORD
